click_log/__init__.py
click_log/core.py
click_log/options.py
click_log-0.3.1.dist-info/DESCRIPTION.rst
click_log-0.3.1.dist-info/METADATA
click_log-0.3.1.dist-info/RECORD
click_log-0.3.1.dist-info/WHEEL
click_log-0.3.1.dist-info/metadata.json
click_log-0.3.1.dist-info/top_level.txt
